{
  "info": {
    "_postman_id": "224d4b73-e72a-4b12-8cd1-d68b1a37d3a0",
    "name": "Scratch Pad",
    "schema": "https://schema.getpostman.com/json/collection/v2.1.0/collection.json",
    "_exporter_id": "1008720"
  },
  "item": [
    {
      "name": "Tech Challenge",
      "item": [
        {
          "name": "Create User",
          "protocolProfileBehavior": {
            "followRedirects": true,
            "disableUrlEncoding": false,
            "disableCookies": false
          },
          "request": {
            "method": "POST",
            "header": [
              {
                "key": "Content-Type",
                "value": "application/json"
              },
              {
                "key": "User-Agent",
                "value": "insomnia/12.5.0"
              }
            ],
            "body": {
              "mode": "raw",
              "raw": "{\n\t\"name\": \"Teste Teste\",\n\t\"email\": \"teste@teste.com\",\n\t\"login\": \"teste\",\n\t\"password\": \"teste\",\n\t\"address\": \"Street one\",\n\t\"profile\": \"CLIENT\"\n}",
              "options": {
                "raw": {
                  "language": "json"
                }
              }
            },
            "url": {
              "raw": "http://localhost:8080/v1/user",
              "protocol": "http",
              "host": [
                "localhost"
              ],
              "port": "8080",
              "path": [
                "v1",
                "user"
              ]
            }
          },
          "response": []
        },
        {
          "name": "Create User - Duplicate email",
          "protocolProfileBehavior": {
            "followRedirects": true,
            "disableUrlEncoding": false,
            "disableCookies": false
          },
          "request": {
            "method": "POST",
            "header": [
              {
                "key": "Content-Type",
                "value": "application/json"
              },
              {
                "key": "User-Agent",
                "value": "insomnia/12.5.0"
              }
            ],
            "body": {
              "mode": "raw",
              "raw": "{\n\t\"name\": \"Teste Teste\",\n\t\"email\": \"teste@teste.com\",\n\t\"login\": \"teste\",\n\t\"password\": \"teste\",\n\t\"address\": \"address one\",\n\t\"profile\": \"CLIENT\"\n}",
              "options": {
                "raw": {
                  "language": "json"
                }
              }
            },
            "url": {
              "raw": "http://localhost:8080/v1/user",
              "protocol": "http",
              "host": [
                "localhost"
              ],
              "port": "8080",
              "path": [
                "v1",
                "user"
              ]
            }
          },
          "response": []
        },
        {
          "name": "Create User - Invalid request",
          "protocolProfileBehavior": {
            "followRedirects": true,
            "disableUrlEncoding": false,
            "disableCookies": false
          },
          "request": {
            "method": "POST",
            "header": [
              {
                "key": "Content-Type",
                "value": "application/json"
              },
              {
                "key": "User-Agent",
                "value": "insomnia/12.5.0"
              }
            ],
            "body": {
              "mode": "raw",
              "raw": "{\n\t\"name\": \"Teste Teste\",\n\t\"email\": \"teste@teste.com\",\n\t\"login\": \"teste\",\n\t\"password\": \"teste\",\n\t\"address\": \"address one\"\n}",
              "options": {
                "raw": {
                  "language": "json"
                }
              }
            },
            "url": {
              "raw": "http://localhost:8080/v1/user",
              "protocol": "http",
              "host": [
                "localhost"
              ],
              "port": "8080",
              "path": [
                "v1",
                "user"
              ]
            }
          },
          "response": []
        },
        {
          "name": "Change password",
          "protocolProfileBehavior": {
            "followRedirects": true,
            "disableUrlEncoding": false,
            "disableCookies": false
          },
          "request": {
            "method": "POST",
            "header": [
              {
                "key": "Content-Type",
                "value": "application/json"
              },
              {
                "key": "User-Agent",
                "value": "insomnia/12.5.0"
              }
            ],
            "body": {
              "mode": "raw",
              "raw": "{\n\t\"email\": \"teste@teste.com\",\n\t\"password\": \"teste\",\n\t\"newPassword\": \"teste2\"\n}",
              "options": {
                "raw": {
                  "language": "json"
                }
              }
            },
            "url": {
              "raw": "http://localhost:8080/v1/user/change-password",
              "protocol": "http",
              "host": [
                "localhost"
              ],
              "port": "8080",
              "path": [
                "v1",
                "user",
                "change-password"
              ]
            }
          },
          "response": []
        },
        {
          "name": "Change password - Invalid",
          "protocolProfileBehavior": {
            "followRedirects": true,
            "disableUrlEncoding": false,
            "disableCookies": false
          },
          "request": {
            "method": "POST",
            "header": [
              {
                "key": "Content-Type",
                "value": "application/json"
              },
              {
                "key": "User-Agent",
                "value": "insomnia/12.5.0"
              }
            ],
            "body": {
              "mode": "raw",
              "raw": "{\n\t\"email\": \"teste@teste.com\",\n\t\"password\": \"teste\",\n\t\"newPassword\": \"teste2\"\n}",
              "options": {
                "raw": {
                  "language": "json"
                }
              }
            },
            "url": {
              "raw": "http://localhost:8080/v1/user/change-password",
              "protocol": "http",
              "host": [
                "localhost"
              ],
              "port": "8080",
              "path": [
                "v1",
                "user",
                "change-password"
              ]
            }
          },
          "response": []
        },
        {
          "name": "Update User",
          "protocolProfileBehavior": {
            "followRedirects": true,
            "disableUrlEncoding": false,
            "disableCookies": false
          },
          "request": {
            "method": "PATCH",
            "header": [
              {
                "key": "Content-Type",
                "value": "application/json"
              },
              {
                "key": "User-Agent",
                "value": "insomnia/12.5.0"
              }
            ],
            "body": {
              "mode": "raw",
              "raw": "{\n\t\"name\": \"Teste Teste Teste\"\n}",
              "options": {
                "raw": {
                  "language": "json"
                }
              }
            },
            "url": {
              "raw": "http://localhost:8080/v1/user/1",
              "protocol": "http",
              "host": [
                "localhost"
              ],
              "port": "8080",
              "path": [
                "v1",
                "user",
                "1"
              ]
            }
          },
          "response": []
        },
        {
          "name": "Update User - Invalid",
          "protocolProfileBehavior": {
            "followRedirects": true,
            "disableUrlEncoding": false,
            "disableCookies": false
          },
          "request": {
            "method": "PATCH",
            "header": [
              {
                "key": "Content-Type",
                "value": "application/json"
              },
              {
                "key": "User-Agent",
                "value": "insomnia/12.5.0"
              }
            ],
            "body": {
              "mode": "raw",
              "raw": "{\n\t\"name\": \"Teste Teste Teste\"\n}",
              "options": {
                "raw": {
                  "language": "json"
                }
              }
            },
            "url": {
              "raw": "http://localhost:8080/v1/user/999",
              "protocol": "http",
              "host": [
                "localhost"
              ],
              "port": "8080",
              "path": [
                "v1",
                "user",
                "999"
              ]
            }
          },
          "response": []
        },
        {
          "name": "Search By Name",
          "protocolProfileBehavior": {
            "followRedirects": true,
            "disableUrlEncoding": false,
            "disableCookies": false
          },
          "request": {
            "method": "GET",
            "header": [
              {
                "key": "User-Agent",
                "value": "insomnia/12.5.0"
              }
            ],
            "url": {
              "raw": "http://localhost:8080/v1/user?name=teste teste teste",
              "protocol": "http",
              "host": [
                "localhost"
              ],
              "port": "8080",
              "path": [
                "v1",
                "user"
              ],
              "query": [
                {
                  "key": "name",
                  "value": "teste teste teste"
                }
              ]
            }
          },
          "response": []
        },
        {
          "name": "Validate Login",
          "protocolProfileBehavior": {
            "followRedirects": true,
            "disableUrlEncoding": false,
            "disableCookies": false
          },
          "request": {
            "method": "POST",
            "header": [
              {
                "key": "Content-Type",
                "value": "application/json"
              },
              {
                "key": "User-Agent",
                "value": "insomnia/12.5.0"
              }
            ],
            "body": {
              "mode": "raw",
              "raw": "{\n\t\"email\": \"teste@teste.com\",\n\t\"password\": \"teste2\"\n}",
              "options": {
                "raw": {
                  "language": "json"
                }
              }
            },
            "url": {
              "raw": "http://localhost:8080/v1/user/valid",
              "protocol": "http",
              "host": [
                "localhost"
              ],
              "port": "8080",
              "path": [
                "v1",
                "user",
                "valid"
              ]
            }
          },
          "response": []
        }
      ]
    }
  ]
}